uneedtest/__init__.py
uneedtest/py.typed
uneedtest-0.1.0.dist-info/WHEEL
uneedtest-0.1.0.dist-info/METADATA
uneedtest-0.1.0.dist-info/LICENSE
uneedtest-0.1.0.dist-info/RECORD
