Metadata-Version: 2.1
Name: uneedtest
Version: 0.1.0
Summary: A snake-cased drop in for unittest.TestCase
Home-page: https://github.com/jonathan-scholbach/uneedtest
License: MIT
Keywords: testing,unittest
Author: Jonathan Scholbach
Author-email: j.scholbach@posteo.de
Requires-Python: >=3.7
Classifier: Development Status :: 4 - Beta
Classifier: Intended Audience :: Developers
Classifier: License :: OSI Approved :: MIT License
Classifier: Programming Language :: Python
Classifier: Programming Language :: Python :: 3
Classifier: Programming Language :: Python :: 3.7
Classifier: Programming Language :: Python :: 3.8
Classifier: Programming Language :: Python :: 3.9
Classifier: Programming Language :: Python :: 3.10
Classifier: Programming Language :: Python :: 3.11
Classifier: Topic :: Software Development :: Testing
Classifier: Topic :: Utilities
Requires-Dist: pyhumps (>=3.0)
Project-URL: Repository, https://github.com/jonathan-scholbach/uneedtest
